paper_reading_framework-0.1.0.dist-info/licenses/LICENSE
src/__init__.py
src/main.py
src/api/__init__.py
src/api/moonshot_client.py
src/implementation/__init__.py
src/implementation/code_generator.py
src/knowledge/__init__.py
src/knowledge/internalizer.py
src/paper/__init__.py
src/paper/fetcher.py
src/paper/parser.py
src/reading/__init__.py
src/reading/glossary_extractor.py
src/reading/guide_generator.py
paper_reading_framework-0.1.0.dist-info/METADATA
paper_reading_framework-0.1.0.dist-info/WHEEL
paper_reading_framework-0.1.0.dist-info/entry_points.txt
paper_reading_framework-0.1.0.dist-info/top_level.txt
paper_reading_framework-0.1.0.dist-info/RECORD
