Metadata-Version: 2.4
Name: paper-reading-framework
Version: 0.1.0
Summary: 使用 Moonshot AI (Kimi) 进行论文的精度阅读、内化和落地的完整框架
Home-page: https://github.com/ocarina1024/paper-reading-framework
Author: Ocarina
Author-email: ocarina1024@gmail.com
Project-URL: Documentation, https://github.com/ocarina1024/paper-reading-framework
Project-URL: Source, https://github.com/ocarina1024/paper-reading-framework
Project-URL: Tracker, https://github.com/ocarina1024/paper-reading-framework/issues
Keywords: paper reading,academic research,AI analysis,Moonshot,Kimi
Classifier: Development Status :: 3 - Alpha
Classifier: Intended Audience :: Developers
Classifier: Intended Audience :: Science/Research
Classifier: License :: OSI Approved :: MIT License
Classifier: Programming Language :: Python :: 3
Classifier: Programming Language :: Python :: 3.8
Classifier: Programming Language :: Python :: 3.9
Classifier: Programming Language :: Python :: 3.10
Classifier: Programming Language :: Python :: 3.11
Classifier: Topic :: Scientific/Engineering
Classifier: Topic :: Software Development :: Libraries :: Python Modules
Requires-Python: >=3.8
License-File: LICENSE
Requires-Dist: requests>=2.31.0
Requires-Dist: openai>=1.0.0
Requires-Dist: python-dotenv>=1.0.0
Requires-Dist: beautifulsoup4>=4.12.0
Requires-Dist: lxml>=4.9.0
Requires-Dist: PyPDF2>=3.0.0
Requires-Dist: markdown>=3.5.0
Requires-Dist: pyyaml>=6.0
Requires-Dist: tqdm>=4.66.0
Requires-Dist: aiohttp>=3.9.0
Dynamic: author
Dynamic: author-email
Dynamic: classifier
Dynamic: description
Dynamic: description-content-type
Dynamic: home-page
Dynamic: keywords
Dynamic: license-file
Dynamic: project-url
Dynamic: requires-dist
Dynamic: requires-python
Dynamic: summary
